GaiaLab/__init__.py
GaiaLab/hits/__init__.py
GaiaLab/hits/hitdetector.py
GaiaLab/hits/hitsimulator.py
GaiaLab/hits/misc.py
GaiaLab/hits/test_hits.py
GaiaLab/hits/filters/__init__.py
GaiaLab/hits/filters/filter_base.py
GaiaLab/hits/filters/kalman.py
GaiaLab/hits/filters/lowpass.py
GaiaLab/hits/filters/test_filter_base.py
GaiaLab/hits/response/__init__.py
GaiaLab/hits/response/anomaly.py
GaiaLab/hits/response/characteristics.py
GaiaLab/hits/response/test_response.py
GaiaLab/scan/__init__.py
GaiaLab/scan/analytic_scanner/__init__.py
GaiaLab/scan/analytic_scanner/agis.py
GaiaLab/scan/analytic_scanner/agis_functions.py
GaiaLab/scan/analytic_scanner/analytic_plots.py
GaiaLab/scan/analytic_scanner/constants.py
GaiaLab/scan/analytic_scanner/frame_transformations.py
GaiaLab/scan/analytic_scanner/helpers.py
GaiaLab/scan/analytic_scanner/quaternion_implementation.py
GaiaLab/scan/analytic_scanner/satellite.py
GaiaLab/scan/analytic_scanner/scanner.py
GaiaLab/scan/analytic_scanner/source.py
GaiaLab/scan/analytic_scanner/test_gaia_lab.py
GaiaLab/scan/geometric_scanner/__init__.py
GaiaLab/scan/geometric_scanner/frame_transformations.py
GaiaLab/scan/geometric_scanner/gaia_geometric_toymodel.py
GaiaLab/scan/geometric_scanner/geometric_animate_zaxis.py
GaiaLab/scan/geometric_scanner/geometric_plots.py
GaiaLab/scan/geometric_scanner/quaternion.py
GaiaLab/scan/geometric_scanner/test_geometric_scanner.py
GaiaLab-0.2.0.dist-info/LICENSE
GaiaLab-0.2.0.dist-info/METADATA
GaiaLab-0.2.0.dist-info/WHEEL
GaiaLab-0.2.0.dist-info/top_level.txt
GaiaLab-0.2.0.dist-info/RECORD
