Metadata-Version: 2.1
Name: GaiaLab
Version: 0.2.0
Summary: Toy model for the Gaia scanning law and micrometeoroid detection and simulation functions for Gaia data.
Home-page: https://github.com/bombrun/GaiaLab
Author: Alex Bombrun, Maria del Valle Varo, Toby James, Luca Zampieri
Author-email: abombrun@sciops.esa.int
License: UNKNOWN
Platform: UNKNOWN
Classifier: Programming Language :: Python :: 3
Classifier: License :: OSI Approved :: MIT License
Classifier: Operating System :: OS Independent
